restack_sdk_cloud/__init__.py
restack_sdk_cloud/errorCodes.py
restack_sdk_cloud/prompts.py
restack_sdk_cloud/restack_cloud.py
restack_sdk_cloud/sdk_types.py
restack_sdk_cloud/utils.py
restack_sdk_cloud/assertions/__init__.py
restack_sdk_cloud/assertions/assertion_stack_plan.py
restack_sdk_cloud-1.0.14.dist-info/METADATA
restack_sdk_cloud-1.0.14.dist-info/WHEEL
restack_sdk_cloud-1.0.14.dist-info/top_level.txt
restack_sdk_cloud-1.0.14.dist-info/RECORD
