Metadata-Version: 2.1
Name: restack-sdk-cloud
Version: 1.0.14
Summary: Deploy to Restack with Cloud SDK
Home-page: https://github.com/restackio/restack-sdk-cloud-py
Author: Restack
Author-email: 
License: MIT
Platform: UNKNOWN
Classifier: Programming Language :: Python :: 3
Classifier: License :: OSI Approved :: MIT License
Classifier: Operating System :: OS Independent
Requires-Python: >=3.6
Requires-Dist: colorama
Requires-Dist: GitPython
Requires-Dist: pydantic
Requires-Dist: requests
